posterior/__init__.py
posterior/distributions.py
posterior/hypotheses.py
posterior/random_variables.py
posterior-0.1.0.dist-info/WHEEL
posterior-0.1.0.dist-info/METADATA
posterior-0.1.0.dist-info/RECORD
